CHANGES.txt
Example.py
ExampleMinimal.py
LICENSE
README.md
__init__.py
deploy.txt
setup.py
DimensionTabler/DefaultConfigs.py
DimensionTabler/DefaultConfigs.pyc
DimensionTabler/DimTab.py
DimensionTabler/DimTab.pyc
DimensionTabler/DimTabConfig.py
DimensionTabler/DimTabConfig.pyc
DimensionTabler/DimTabEvArgs.py
DimensionTabler/DimTabEvArgs.pyc
DimensionTabler/__init__.py
DimensionTabler/__init__.pyc
DimensionTabler.egg-info/PKG-INFO
DimensionTabler.egg-info/SOURCES.txt
DimensionTabler.egg-info/dependency_links.txt
DimensionTabler.egg-info/requires.txt
DimensionTabler.egg-info/top_level.txt
DimensionTabler/_libs/Cumulator.py
DimensionTabler/_libs/DimTabWorker.py
DimensionTabler/_libs/SchemaUpdater.py
DimensionTabler/_libs/__init__.py
DimensionTabler/_utils/__init__.py
DimensionTabler/_utils/callbackHandler.py
DimensionTabler/_utils/datetimeUtil.py
DimensionTabler/_utils/dbHandler.py
DimensionTabler/_utils/fx.py
DimensionTabler/_utils/fxHandler.py
DimensionTabler/_utils/iterUtil.py
DimensionTabler/_utils/myDict.py
DimensionTabler/_vo/DimensionTableRow.py
DimensionTabler/_vo/Dimensions.py
DimensionTabler/_vo/EvArgsBase.py
DimensionTabler/_vo/GroupedRows.py
DimensionTabler/_vo/MyIterBase.py
DimensionTabler/_vo/SourceRow.py
DimensionTabler/_vo/__init__.py