Metadata-Version: 1.1
Name: DimensionTabler
Version: 0.1.6
Summary: Builds dimension tables with configurable/variable grainularity.Keeps those tables up-to-date. This makes reporting queries performant and doable. I use it with grafana.
Home-page: https://github.com/LaggAt/DimensionTabler
Author: Florian Lagg
Author-email: github@florian.lagg.at
License: GPL v3
Keywords: dimension tables database grafana bi business intelligence
Platform: UNKNOWN
Classifier: Development Status :: 3 - Alpha
Classifier: Intended Audience :: Developers
Classifier: Intended Audience :: Science/Research
Classifier: Programming Language :: Python :: 2.7
Classifier: Topic :: Utilities
Classifier: Topic :: Database
Classifier: Topic :: Office/Business :: Financial
Classifier: License :: OSI Approved :: GNU General Public License v3 (GPLv3)
